odoo10_addon_account_product_fiscal_classification-10.0.1.0.0.99.dev25-py3.8-nspkg.pth
odoo/addons/account_product_fiscal_classification/README.rst
odoo/addons/account_product_fiscal_classification/__init__.py
odoo/addons/account_product_fiscal_classification/__manifest__.py
odoo/addons/account_product_fiscal_classification/demo/account_product_fiscal_classification.yml
odoo/addons/account_product_fiscal_classification/demo/account_product_fiscal_classification_template.yml
odoo/addons/account_product_fiscal_classification/demo/account_tax.yml
odoo/addons/account_product_fiscal_classification/demo/account_tax_template.yml
odoo/addons/account_product_fiscal_classification/demo/product_category.xml
odoo/addons/account_product_fiscal_classification/demo/product_template.yml
odoo/addons/account_product_fiscal_classification/demo/res_company.yml
odoo/addons/account_product_fiscal_classification/demo/res_groups.yml
odoo/addons/account_product_fiscal_classification/demo/res_users.yml
odoo/addons/account_product_fiscal_classification/i18n/account_product_fiscal_classification.pot
odoo/addons/account_product_fiscal_classification/i18n/am.po
odoo/addons/account_product_fiscal_classification/i18n/ar.po
odoo/addons/account_product_fiscal_classification/i18n/bg.po
odoo/addons/account_product_fiscal_classification/i18n/bs.po
odoo/addons/account_product_fiscal_classification/i18n/ca.po
odoo/addons/account_product_fiscal_classification/i18n/ca_ES.po
odoo/addons/account_product_fiscal_classification/i18n/cs.po
odoo/addons/account_product_fiscal_classification/i18n/da.po
odoo/addons/account_product_fiscal_classification/i18n/de.po
odoo/addons/account_product_fiscal_classification/i18n/el_GR.po
odoo/addons/account_product_fiscal_classification/i18n/en_AU.po
odoo/addons/account_product_fiscal_classification/i18n/en_GB.po
odoo/addons/account_product_fiscal_classification/i18n/es.po
odoo/addons/account_product_fiscal_classification/i18n/es_AR.po
odoo10_addon_account_product_fiscal_classification-10.0.1.0.0.99.dev25.dist-info/METADATA
odoo10_addon_account_product_fiscal_classification-10.0.1.0.0.99.dev25.dist-info/WHEEL
odoo10_addon_account_product_fiscal_classification-10.0.1.0.0.99.dev25.dist-info/namespace_packages.txt
odoo10_addon_account_product_fiscal_classification-10.0.1.0.0.99.dev25.dist-info/top_level.txt
odoo10_addon_account_product_fiscal_classification-10.0.1.0.0.99.dev25.dist-info/RECORD
